pt_loop.py
pt_loop-0.1.0.dist-info/licenses/LICENSE
pt_loop-0.1.0.dist-info/METADATA
pt_loop-0.1.0.dist-info/WHEEL
pt_loop-0.1.0.dist-info/top_level.txt
pt_loop-0.1.0.dist-info/RECORD
