Metadata-Version: 2.4
Name: pt_loop
Version: 0.1.0
Summary: Local Outlier Probabilities (LoOP) implementation in PyTorch
Author: Ofer Hasson
License-Expression: Apache-2.0
Project-URL: Homepage, https://gitlab.com/hassonofer/pt_loop
Project-URL: Issues, https://gitlab.com/hassonofer/pt_loop/-/issues
Keywords: pytorch,loop,outlier-detection,anomaly-detection,machine-learning,unsupervised-learning
Classifier: Development Status :: 4 - Beta
Classifier: Intended Audience :: Science/Research
Classifier: Operating System :: OS Independent
Classifier: Programming Language :: Python :: 3
Classifier: Topic :: Scientific/Engineering
Classifier: Topic :: Scientific/Engineering :: Artificial Intelligence
Classifier: Topic :: Software Development
Classifier: Topic :: Software Development :: Libraries
Classifier: Topic :: Software Development :: Libraries :: Python Modules
Requires-Python: >=3.11
License-File: LICENSE
Requires-Dist: torch>=2.4.0
Dynamic: license-file
